geocode/__init__.py
geocode/flags.py
geocode/geocode.py
geocode/data/geonames_6b64aaafc53116f.pkl
geocode/data/geonames_keyword_processor_6b64aaafc53116f.pkl
local_geocode-0.0.2.dist-info/LICENSE
local_geocode-0.0.2.dist-info/METADATA
local_geocode-0.0.2.dist-info/WHEEL
local_geocode-0.0.2.dist-info/top_level.txt
local_geocode-0.0.2.dist-info/RECORD
