Metadata-Version: 2.1
Name: local-geocode
Version: 0.0.2
Summary: Simple library for efficient geocoding without making API calls
Home-page: https://github.com/mar-muel/local-geocode
Author: Martin Müller
Author-email: martin.mathias.mueller@gmail.com
Classifier: Programming Language :: Python :: 3
Classifier: License :: OSI Approved :: MIT License
Classifier: Operating System :: OS Independent
Requires-Python: >=3.6
License-File: LICENSE
Requires-Dist: pandas
Requires-Dist: tqdm
Requires-Dist: flashtext
Requires-Dist: joblib
